abx_spec_abx_pkg.py
abx_spec_abx_pkg-0.1.1.dist-info/METADATA
abx_spec_abx_pkg-0.1.1.dist-info/WHEEL
abx_spec_abx_pkg-0.1.1.dist-info/entry_points.txt
abx_spec_abx_pkg-0.1.1.dist-info/RECORD
